<template>
	<MainPage site=""></MainPage>
	<Node>&lt;th class="subject"&gt;(.+?)&lt;/tbody&gt;</Node>
	<Title>
		aspx"&gt;(.+?)&lt;/a&gt;
	</Title>
	<Author>
		class="xg2"&gt;(\d+)&lt;/a&gt;
	</Author>
	<ContentDate>
		id="message\d+" class="t_msgfont"&gt;(.+?)&lt;/tr
	</ContentDate>
	<Content>
		id="message\d+" class="t_msgfont"&gt;(.+?)&lt;/tr
	</Content>
	<Views>&lt;em&gt;(\d+)&lt;/em&gt;</Views>
	<Replies>class="xg2"&gt;(\d+)&lt;/a&gt;</Replies>
	<SrcUrl>&lt;/em&gt;.+?href="(.+?)"&gt;</SrcUrl>
	<Url>http://bbs.wzcbd.com/showforum-29.aspx</Url>
	<SiteEncoding>UTF-8</SiteEncoding>
	<InnerEncoding>UTF-8</InnerEncoding>
	 <Layer>2</Layer>
	<SiteName>forum</SiteName>
	<NextPage />
</template>