<template>
	<MainPage site=""></MainPage>
	<Node>valign="middle"&gt;·(.+?)&lt;/tr</Node>
	<Title>
		&lt;a.+?&gt;(.+?)&lt;/a
	</Title>
	<ContentDate>
		span class="n10"&gt;(.+?)&lt;/span&gt;	
	</ContentDate>
	<Content>
		enpcontent--&gt;(.+?)&lt;/div
	</Content>
	<Views></Views>
	<Replies></Replies>
	<Author></Author>
	<SrcUrl>&lt;a href=(.+?) target=</SrcUrl>
	<Url>http://news.my399.com/video/</Url>
	<SiteEncoding>GB2312</SiteEncoding>
	<InnerEncoding>GB2312</InnerEncoding>
	<Layer>2</Layer>
    <SiteName>forum</SiteName>
	<NextPage />
</template>